discord_send_embed/__init__.py
discord_send_embed-0.0.3.dist-info/METADATA
discord_send_embed-0.0.3.dist-info/WHEEL
discord_send_embed-0.0.3.dist-info/licenses/LICENSE
discord_send_embed-0.0.3.dist-info/RECORD
