Metadata-Version: 2.1
Name: discord_send_embed
Version: 0.0.3
Summary: Helper for sending embeds with discord.py or its forks
Project-URL: Homepage, https://github.com/victorbnl/discord-send-embed
Project-URL: Bug Tracker, https://github.com/victorbnl/discord-send-embed/issues
Author-email: Victor Bonnelle <victor.bonnelle@proton.me>
License: MIT
Requires-Python: >=3.7
